neo/Settings.py
neo/__init__.py
neo/Network/__init__.py
neo/Network/RPC/Client.py
neo/Network/RPC/__init__.py
neorpc/Client.py
neorpc/Settings.py
neorpc/__init__.py
neorpc_python_rpc-0.1.6.dist-info/DESCRIPTION.rst
neorpc_python_rpc-0.1.6.dist-info/METADATA
neorpc_python_rpc-0.1.6.dist-info/RECORD
neorpc_python_rpc-0.1.6.dist-info/WHEEL
neorpc_python_rpc-0.1.6.dist-info/metadata.json
neorpc_python_rpc-0.1.6.dist-info/top_level.txt
