Metadata-Version: 2.0
Name: neorpc-python-rpc
Version: 0.1.6
Summary: A Python RPC Client for the NEO Blockchain
Home-page: https://github.com/CityOfZion/neorpc-python-rpc
Author: Thomas Saunders
Author-email: tom@cityofzion.io
License: MIT license
Keywords: neorpc,python,rpc,client
Platform: UNKNOWN
Classifier: Development Status :: 2 - Pre-Alpha
Classifier: Intended Audience :: Developers
Classifier: License :: OSI Approved :: MIT License
Classifier: Natural Language :: English
Classifier: Programming Language :: Python :: 3
Classifier: Programming Language :: Python :: 3.3
Classifier: Programming Language :: Python :: 3.4
Classifier: Programming Language :: Python :: 3.5
Requires-Dist: requests
